exdata/__init__.py
exdata/exceptions.py
exdata/exporter.py
exdata/struct.py
exdata-0.1.2.dist-info/METADATA
exdata-0.1.2.dist-info/WHEEL
exdata-0.1.2.dist-info/licenses/LICENSE.md
exdata-0.1.2.dist-info/RECORD
