Metadata-Version: 2.4
Name: exdata
Version: 0.1.2
Summary: Export data to xlsx
Project-URL: Homepage, https://github.com/kindlycat/exdata
Project-URL: Documentation, https://exdata.readthedocs.io
Project-URL: Repository, https://github.com/kindlycat/exdata.git
Project-URL: Issues, https://github.com/kindlycat/exdata/issues
Author-email: Grigory Mishchenko <grishkokot@gmail.com>
License-Expression: MIT
License-File: LICENSE.md
Keywords: data,excel,export,xlsx,xlsxwriter
Classifier: Development Status :: 4 - Beta
Classifier: License :: OSI Approved :: MIT License
Classifier: Programming Language :: Python :: 3.10
Classifier: Programming Language :: Python :: 3.11
Classifier: Programming Language :: Python :: 3.12
Classifier: Programming Language :: Python :: 3.13
Requires-Python: >=3.10
Requires-Dist: xlsxwriter>=3.2.3
